{
  "cliente": "fidez_group",
  "fase_actual": "2_onboarding",
  "actualizado": "2026-05-06T15:32:42+00:00",
  "gates": {
    "1_comercial": "closed",
    "2_onboarding": "closed",
    "3_preproduccion": "open",
    "4_produccion": "blocked",
    "5_pauta": "blocked",
    "6_lanzamiento": "blocked"
  },
  "evidencia": {
    "brand_json": true,
    "guiones": 0,
    "briefs_carrusel": 0,
    "estrategias": 0,
    "copy_meta_ads": 0,
    "captions": 0,
    "disenos_png": 0,
    "plan_campana": 0,
    "brief_creativo_pauta": 0,
    "campanas_meta_creadas": false,
    "reporte_reciente": false
  },
  "siguiente_accion": {
    "fase_pendiente": "3_preproduccion",
    "owner": "Nico (Creative Director)",
    "tarea": "Generar guiones y briefs de carrusel",
    "trigger": "creative_director: estrategia mensual"
  }
}